m3stat/__init__.py
m3stat-0.0.1.dist-info/LICENSE
m3stat-0.0.1.dist-info/METADATA
m3stat-0.0.1.dist-info/WHEEL
m3stat-0.0.1.dist-info/top_level.txt
m3stat-0.0.1.dist-info/RECORD
