Metadata-Version: 2.1
Name: m3stat
Version: 0.0.1
Summary: A small package for mean, median, mode
Author-email: Burhan Uddin <burhan8.314@protonmail.com>
Classifier: Programming Language :: Python :: 3
Classifier: Operating System :: OS Independent
Requires-Python: >=3.8
License-File: LICENSE
